nnClassify-0.0.31.dist-info/DESCRIPTION.rst
nnClassify-0.0.31.dist-info/METADATA
nnClassify-0.0.31.dist-info/RECORD
nnClassify-0.0.31.dist-info/WHEEL
nnClassify-0.0.31.dist-info/entry_points.txt
nnClassify-0.0.31.dist-info/metadata.json
nnClassify-0.0.31.dist-info/top_level.txt
src/Constants.py
src/Evaluator_.py
src/ImageCropper_.py
src/Main_.py
src/MyUtils_.py
src/NeuralNetwork_.py
src/Pickler_.py
src/Predictor_.py
src/Transfer_Calculator_.py
src/__init__.py
src/cache.py
src/dataset.py
src/download.py
src/inception.py
src/inception5h.py
src/scripts.py
