Metadata-Version: 2.0
Name: nnClassify
Version: 0.0.31
Summary: A command line tool for classifying images using transfer learning
Home-page: https://github.com/PatrickgHayes/nnClassify
Author: Patrick Hayes and Aaron Graham
Author-email: patrickghayes@gmail.com
License: MIT
Keywords: image classification transfer learning
Platform: UNKNOWN
Classifier: Development Status :: 3 - Alpha
Classifier: License :: OSI Approved :: MIT License
Classifier: Programming Language :: Python :: 3
